[
    {
        "id": "0x0521aaa7c96e25afee79fdd4f1bb48f008ae4eac",
        "chain": "base",
        "name": "DR3AM Fund",
        "symbol": "FDREAM",
        "display_symbol": null,
        "optimized_symbol": "FDREAM",
        "decimals": 18,
        "logo_url": "https://static.debank.com/image/base_token/logo_url/0x0521aaa7c96e25afee79fdd4f1bb48f008ae4eac/ff17265347835e9ef0884f926c3516d0.png",
        "protocol_id": "",
        "price": 0.0035059872686776144,
        "price_24h_change": -0.28537213660058314,
        "is_verified": false,
        "is_core": true,
        "is_wallet": true,
        "time_at": 1735352833,
        "amount": 20000000,
        "raw_amount": 2e+25,
        "raw_amount_hex_str": "0x108b2a2c28029094000000"
    },
    {
        "id": "0x07d15798a67253d76cea61f0ea6f57aedc59dffb",
        "chain": "base",
        "name": "Based Coin",
        "symbol": "BASED",
        "display_symbol": "BASED (unknown)",
        "optimized_symbol": "BASED (unknown)",
        "decimals": 18,
        "logo_url": "https://static.debank.com/image/base_token/logo_url/0x07d15798a67253d76cea61f0ea6f57aedc59dffb/892d5d2a0dafb79d97e451760536f528.png",
        "protocol_id": "base_basedcoin",
        "price": 0.00003858134716723185,
        "price_24h_change": 0.017368769310313337,
        "is_verified": true,
        "is_core": true,
        "is_wallet": true,
        "time_at": 1711681777,
        "amount": 350,
        "raw_amount": 350000000000000000000,
        "raw_amount_hex_str": "0x12f939c99edab80000"
    },
    {
        "id": "0x20ef84969f6d81ff74ae4591c331858b20ad82cd",
        "chain": "base",
        "name": "AicroStrategy",
        "symbol": "AiSTR",
        "display_symbol": null,
        "optimized_symbol": "AiSTR",
        "decimals": 18,
        "logo_url": "https://static.debank.com/image/base_token/logo_url/0x20ef84969f6d81ff74ae4591c331858b20ad82cd/a3b9e285ddb66766be135a16bc3f66fe.png",
        "protocol_id": "",
        "price": 0.0038252626779969367,
        "price_24h_change": 0.3939161049917216,
        "is_verified": false,
        "is_core": true,
        "is_wallet": true,
        "time_at": 1734922801,
        "amount": 1.054e-15,
        "raw_amount": 1054,
        "raw_amount_hex_str": "0x41e"
    },
    {
        "id": "0x2b0772bea2757624287ffc7feb92d03aeae6f12d",
        "chain": "base",
        "name": "Alchemist Accelerate",
        "symbol": "ALCH",
        "display_symbol": null,
        "optimized_symbol": "ALCH",
        "decimals": 18,
        "logo_url": "https://static.debank.com/image/base_token/logo_url/0x2b0772bea2757624287ffc7feb92d03aeae6f12d/ed3cdac83c2ff6794d16153ae1b32e49.png",
        "protocol_id": "",
        "price": 0.0008014046827510698,
        "price_24h_change": -0.17582214775996624,
        "is_verified": false,
        "is_core": true,
        "is_wallet": true,
        "time_at": 1735045713,
        "amount": 5000000,
        "raw_amount": 5e+24,
        "raw_amount_hex_str": "0x422ca8b0a00a425000000"
    },
    {
        "id": "0x3e64cd8fd4d2fae3d7f4710817885b0941838d0b",
        "chain": "base",
        "name": "3 Beras Capital",
        "symbol": "3BC",
        "display_symbol": null,
        "optimized_symbol": "3BC",
        "decimals": 18,
        "logo_url": "https://static.debank.com/image/base_token/logo_url/0x3e64cd8fd4d2fae3d7f4710817885b0941838d0b/36943cbdb36a45d0bd83aee582c73529.png",
        "protocol_id": "",
        "price": 0.0038881379013708107,
        "price_24h_change": -0.12468942487467194,
        "is_verified": false,
        "is_core": true,
        "is_wallet": true,
        "time_at": 1736398517,
        "amount": 5347826.0869565215,
        "raw_amount": 5.347826086956522e+24,
        "raw_amount_hex_str": "0x46c723baafa01edb21642"
    },
    {
        "id": "0x543257ef2161176d7c8cd90ba65c2d4caef5a796",
        "chain": "base",
        "name": "Moonwell Frontier cbBTC",
        "symbol": "mwcbBTC",
        "display_symbol": null,
        "optimized_symbol": "mwcbBTC",
        "decimals": 18,
        "logo_url": null,
        "protocol_id": "base_morphoblue",
        "price": 113874.27514830513,
        "price_24h_change": null,
        "is_verified": false,
        "is_core": false,
        "is_wallet": false,
        "time_at": 1732609545,
        "amount": 0.8297413146974222,
        "raw_amount": 829741314697422200,
        "raw_amount_hex_str": "0xb83d5545e016557"
    },
    {
        "id": "0x623cd3a3edf080057892aaf8d773bbb7a5c9b6e9",
        "chain": "base",
        "name": "Sekuya",
        "symbol": "SKYA",
        "display_symbol": null,
        "optimized_symbol": "SKYA",
        "decimals": 18,
        "logo_url": "https://static.debank.com/image/base_token/logo_url/0x623cd3a3edf080057892aaf8d773bbb7a5c9b6e9/b82923ee85a1f6477eed780357b3484c.png",
        "protocol_id": "",
        "price": 0.017829278003780074,
        "price_24h_change": -0.059994234110547856,
        "is_verified": false,
        "is_core": true,
        "is_wallet": true,
        "time_at": 1715259495,
        "amount": 15.549,
        "raw_amount": 15549000000000000000,
        "raw_amount_hex_str": "0xd7c9251e2c8c8000"
    },
    {
        "id": "0x73326b4d0225c429bed050c11c4422d91470aaf4",
        "chain": "base",
        "name": "DACKIE Superchain",
        "symbol": "DACKIE",
        "display_symbol": "DACKIE (Superchain)",
        "optimized_symbol": "DACKIE (Superchain)",
        "decimals": 18,
        "logo_url": "https://static.debank.com/image/base_token/logo_url/0x73326b4d0225c429bed050c11c4422d91470aaf4/ad20d5c24897f798395f9d5b35503ff5.png",
        "protocol_id": "",
        "price": 0.020312949090158038,
        "price_24h_change": 0.03125523180175529,
        "is_verified": false,
        "is_core": true,
        "is_wallet": true,
        "time_at": 1734667045,
        "amount": 50000,
        "raw_amount": 5e+22,
        "raw_amount_hex_str": "0xa968163f0a57b400000"
    },
    {
        "id": "0x74ccbe53f77b08632ce0cb91d3a545bf6b8e0979",
        "chain": "base",
        "name": "Fantom Bomb",
        "symbol": "fBOMB",
        "display_symbol": null,
        "optimized_symbol": "fBOMB",
        "decimals": 18,
        "logo_url": "https://static.debank.com/image/base_token/logo_url/0x74ccbe53f77b08632ce0cb91d3a545bf6b8e0979/1a2556a9965b8afa4f97b6fdf5029f1e.png",
        "protocol_id": "",
        "price": 0.05019330930369936,
        "price_24h_change": 0.013921278878271897,
        "is_verified": true,
        "is_core": true,
        "is_wallet": true,
        "time_at": 1691002561,
        "amount": 83921.4407484089,
        "raw_amount": 8.392144074840891e+22,
        "raw_amount_hex_str": "0x11c563f27dd420e4913d"
    },
    {
        "id": "0x940181a94a35a4569e4529a3cdfb74e38fd98631",
        "chain": "base",
        "name": "Aerodrome",
        "symbol": "AERO",
        "display_symbol": null,
        "optimized_symbol": "AERO",
        "decimals": 18,
        "logo_url": "https://static.debank.com/image/base_token/logo_url/0x940181a94a35a4569e4529a3cdfb74e38fd98631/bb455b8557be5d08ad67f4314f899e15.png",
        "protocol_id": "base_aerodrome3",
        "price": 1.102500320282252,
        "price_24h_change": -0.041647584847720326,
        "is_verified": true,
        "is_core": true,
        "is_wallet": true,
        "time_at": 1693190447,
        "amount": 135.18001244818743,
        "raw_amount": 135180012448187430000,
        "raw_amount_hex_str": "0x753ffe11b73183c62"
    },
    {
        "id": "0xcbb7c0000ab88b473b1f5afd9ef808440eed33bf",
        "chain": "base",
        "name": "Coinbase Wrapped BTC",
        "symbol": "cbBTC",
        "display_symbol": null,
        "optimized_symbol": "cbBTC",
        "decimals": 8,
        "logo_url": "https://static.debank.com/image/base_token/logo_url/0xcbb7c0000ab88b473b1f5afd9ef808440eed33bf/a4ae837a6ca2fc45f07a74898cc4ba45.png",
        "protocol_id": "",
        "price": 94485.51554270758,
        "price_24h_change": 0.006271454912182246,
        "is_verified": false,
        "is_core": true,
        "is_wallet": true,
        "time_at": 1724165535,
        "amount": 0.00468304,
        "raw_amount": 468304,
        "raw_amount_hex_str": "0x72550"
    },
    {
        "id": "0xe278d598901153db1402456fda324f148e586871",
        "chain": "base",
        "name": "Yampi",
        "symbol": "YMP",
        "display_symbol": null,
        "optimized_symbol": "YMP",
        "decimals": 18,
        "logo_url": null,
        "protocol_id": "",
        "price": 0,
        "price_24h_change": null,
        "is_verified": false,
        "is_core": false,
        "is_wallet": false,
        "time_at": 1735734715,
        "amount": 200,
        "raw_amount": 200000000000000000000,
        "raw_amount_hex_str": "0xad78ebc5ac6200000"
    },
    {
        "id": "0xebf418fe2512e7e6bd9b87a8f0f294acdc67e6b4",
        "chain": "base",
        "name": "veNFT",
        "symbol": "veNFT",
        "display_symbol": null,
        "optimized_symbol": "veNFT",
        "decimals": 18,
        "logo_url": null,
        "protocol_id": "base_aerodrome",
        "price": 0,
        "price_24h_change": null,
        "is_verified": true,
        "is_core": false,
        "is_wallet": false,
        "time_at": 1693190515,
        "amount": 1e-18,
        "raw_amount": 1,
        "raw_amount_hex_str": "0x1"
    },
    {
        "id": "0xed7c6bf8756a40fb6d9b180a8552e4c493511252",
        "chain": "base",
        "name": "Nike",
        "symbol": "NIKE",
        "display_symbol": null,
        "optimized_symbol": "NIKE",
        "decimals": 18,
        "logo_url": "https://static.debank.com/image/base_token/logo_url/0xed7c6bf8756a40fb6d9b180a8552e4c493511252/050144ce838eec264a60f87012dfb2e3.png",
        "protocol_id": "",
        "price": 0,
        "price_24h_change": -0.7915357077993793,
        "is_verified": false,
        "is_core": false,
        "is_wallet": false,
        "time_at": 1734950573,
        "amount": 400,
        "raw_amount": 400000000000000000000,
        "raw_amount_hex_str": "0x15af1d78b58c400000"
    },
    {
        "id": "base",
        "chain": "base",
        "name": "ETH",
        "symbol": "ETH",
        "display_symbol": null,
        "optimized_symbol": "ETH",
        "decimals": 18,
        "logo_url": "https://static.debank.com/image/coin/logo_url/eth/6443cdccced33e204d90cb723c632917.png",
        "protocol_id": "",
        "price": 3274.34,
        "price_24h_change": 0.006468838531269191,
        "is_verified": true,
        "is_core": true,
        "is_wallet": true,
        "time_at": null,
        "amount": 0.7108527002015254,
        "raw_amount": 710852700201525400,
        "raw_amount_hex_str": "0x9dd74c3bb23a06a"
    }
]